[
  {
    "athlete": "Meghan Agosta",
    "age": 23,
    "country": "Canada",
    "year": 2010,
    "date": "28/02/2010",
    "sport": "Ice Hockey",
    "gold": 1,
    "silver": 0,
    "bronze": 0,
    "total": 1
  },
  {
    "athlete": "Gillian Apps",
    "age": 26,
    "country": "Canada",
    "year": 2010,
    "date": "28/02/2010",
    "sport": "Ice Hockey",
    "gold": 1,
    "silver": 0,
    "bronze": 0,
    "total": 1
  },
  {
    "athlete": "Patrice Bergeron-Cleary",
    "age": 24,
    "country": "Canada",
    "year": 2010,
    "date": "28/02/2010",
    "sport": "Ice Hockey",
    "gold": 1,
    "silver": 0,
    "bronze": 0,
    "total": 1
  },
  {
    "athlete": "Tessa Bonhomme",
    "age": 24,
    "country": "Canada",
    "year": 2010,
    "date": "28/02/2010",
    "sport": "Ice Hockey",
    "gold": 1,
    "silver": 0,
    "bronze": 0,
    "total": 1
  },
  {
    "athlete": "Jennifer Botterill",
    "age": 30,
    "country": "Canada",
    "year": 2010,
    "date": "28/02/2010",
    "sport": "Ice Hockey",
    "gold": 1,
    "silver": 0,
    "bronze": 0,
    "total": 1
  },
  {
    "athlete": "Dan Boyle",
    "age": 33,
    "country": "Canada",
    "year": 2010,
    "date": "28/02/2010",
    "sport": "Ice Hockey",
    "gold": 1,
    "silver": 0,
    "bronze": 0,
    "total": 1
  },
  {
    "athlete": "Martin Brodeur",
    "age": 37,
    "country": "Canada",
    "year": 2010,
    "date": "28/02/2010",
    "sport": "Ice Hockey",
    "gold": 1,
    "silver": 0,
    "bronze": 0,
    "total": 1
  },
  {
    "athlete": "Sidney Crosby",
    "age": 22,
    "country": "Canada",
    "year": 2010,
    "date": "28/02/2010",
    "sport": "Ice Hockey",
    "gold": 1,
    "silver": 0,
    "bronze": 0,
    "total": 1
  },
  {
    "athlete": "Drew Doughty",
    "age": 20,
    "country": "Canada",
    "year": 2010,
    "date": "28/02/2010",
    "sport": "Ice Hockey",
    "gold": 1,
    "silver": 0,
    "bronze": 0,
    "total": 1
  },
  {
    "athlete": "Ryan Getzlaf",
    "age": 24,
    "country": "Canada",
    "year": 2010,
    "date": "28/02/2010",
    "sport": "Ice Hockey",
    "gold": 1,
    "silver": 0,
    "bronze": 0,
    "total": 1
  },
  {
    "athlete": "Dany Heatley",
    "age": 29,
    "country": "Canada",
    "year": 2010,
    "date": "28/02/2010",
    "sport": "Ice Hockey",
    "gold": 1,
    "silver": 0,
    "bronze": 0,
    "total": 1
  },
  {
    "athlete": "Jayna Hefford",
    "age": 32,
    "country": "Canada",
    "year": 2010,
    "date": "28/02/2010",
    "sport": "Ice Hockey",
    "gold": 1,
    "silver": 0,
    "bronze": 0,
    "total": 1
  },
  {
    "athlete": "Jarome Iginla",
    "age": 32,
    "country": "Canada",
    "year": 2010,
    "date": "28/02/2010",
    "sport": "Ice Hockey",
    "gold": 1,
    "silver": 0,
    "bronze": 0,
    "total": 1
  },
  {
    "athlete": "Haley Irwin",
    "age": 21,
    "country": "Canada",
    "year": 2010,
    "date": "28/02/2010",
    "sport": "Ice Hockey",
    "gold": 1,
    "silver": 0,
    "bronze": 0,
    "total": 1
  },
  {
    "athlete": "Rebecca Johnston",
    "age": 20,
    "country": "Canada",
    "year": 2010,
    "date": "28/02/2010",
    "sport": "Ice Hockey",
    "gold": 1,
    "silver": 0,
    "bronze": 0,
    "total": 1
  },
  {
    "athlete": "Duncan Keith",
    "age": 26,
    "country": "Canada",
    "year": 2010,
    "date": "28/02/2010",
    "sport": "Ice Hockey",
    "gold": 1,
    "silver": 0,
    "bronze": 0,
    "total": 1
  },
  {
    "athlete": "Becky Kellar",
    "age": 35,
    "country": "Canada",
    "year": 2010,
    "date": "28/02/2010",
    "sport": "Ice Hockey",
    "gold": 1,
    "silver": 0,
    "bronze": 0,
    "total": 1
  },
  {
    "athlete": "Gina Kingsbury",
    "age": 28,
    "country": "Canada",
    "year": 2010,
    "date": "28/02/2010",
    "sport": "Ice Hockey",
    "gold": 1,
    "silver": 0,
    "bronze": 0,
    "total": 1
  },
  {
    "athlete": "Charlie Labonté",
    "age": 27,
    "country": "Canada",
    "year": 2010,
    "date": "28/02/2010",
    "sport": "Ice Hockey",
    "gold": 1,
    "silver": 0,
    "bronze": 0,
    "total": 1
  },
  {
    "athlete": "Roberto Luongo",
    "age": 30,
    "country": "Canada",
    "year": 2010,
    "date": "28/02/2010",
    "sport": "Ice Hockey",
    "gold": 1,
    "silver": 0,
    "bronze": 0,
    "total": 1
  },
  {
    "athlete": "Carla MacLeod",
    "age": 27,
    "country": "Canada",
    "year": 2010,
    "date": "28/02/2010",
    "sport": "Ice Hockey",
    "gold": 1,
    "silver": 0,
    "bronze": 0,
    "total": 1
  },
  {
    "athlete": "Patrick Marleau",
    "age": 30,
    "country": "Canada",
    "year": 2010,
    "date": "28/02/2010",
    "sport": "Ice Hockey",
    "gold": 1,
    "silver": 0,
    "bronze": 0,
    "total": 1
  },
  {
    "athlete": "Meaghan Mikkelson",
    "age": 25,
    "country": "Canada",
    "year": 2010,
    "date": "28/02/2010",
    "sport": "Ice Hockey",
    "gold": 1,
    "silver": 0,
    "bronze": 0,
    "total": 1
  },
  {
    "athlete": "Brenden Morrow",
    "age": 31,
    "country": "Canada",
    "year": 2010,
    "date": "28/02/2010",
    "sport": "Ice Hockey",
    "gold": 1,
    "silver": 0,
    "bronze": 0,
    "total": 1
  },
  {
    "athlete": "Rick Nash",
    "age": 25,
    "country": "Canada",
    "year": 2010,
    "date": "28/02/2010",
    "sport": "Ice Hockey",
    "gold": 1,
    "silver": 0,
    "bronze": 0,
    "total": 1
  },
  {
    "athlete": "Scott Niedermayer",
    "age": 36,
    "country": "Canada",
    "year": 2010,
    "date": "28/02/2010",
    "sport": "Ice Hockey",
    "gold": 1,
    "silver": 0,
    "bronze": 0,
    "total": 1
  },
  {
    "athlete": "Caroline Ouellette",
    "age": 30,
    "country": "Canada",
    "year": 2010,
    "date": "28/02/2010",
    "sport": "Ice Hockey",
    "gold": 1,
    "silver": 0,
    "bronze": 0,
    "total": 1
  },
  {
    "athlete": "Corey Perry",
    "age": 24,
    "country": "Canada",
    "year": 2010,
    "date": "28/02/2010",
    "sport": "Ice Hockey",
    "gold": 1,
    "silver": 0,
    "bronze": 0,
    "total": 1
  },
  {
    "athlete": "Cherie Piper",
    "age": 28,
    "country": "Canada",
    "year": 2010,
    "date": "28/02/2010",
    "sport": "Ice Hockey",
    "gold": 1,
    "silver": 0,
    "bronze": 0,
    "total": 1
  },
  {
    "athlete": "Marie-Philip Poulin",
    "age": 18,
    "country": "Canada",
    "year": 2010,
    "date": "28/02/2010",
    "sport": "Ice Hockey",
    "gold": 1,
    "silver": 0,
    "bronze": 0,
    "total": 1
  },
  {
    "athlete": "Chris Pronger",
    "age": 35,
    "country": "Canada",
    "year": 2010,
    "date": "28/02/2010",
    "sport": "Ice Hockey",
    "gold": 1,
    "silver": 0,
    "bronze": 0,
    "total": 1
  },
  {
    "athlete": "Mike Richards",
    "age": 25,
    "country": "Canada",
    "year": 2010,
    "date": "28/02/2010",
    "sport": "Ice Hockey",
    "gold": 1,
    "silver": 0,
    "bronze": 0,
    "total": 1
  },
  {
    "athlete": "Brent Seabrook",
    "age": 24,
    "country": "Canada",
    "year": 2010,
    "date": "28/02/2010",
    "sport": "Ice Hockey",
    "gold": 1,
    "silver": 0,
    "bronze": 0,
    "total": 1
  },
  {
    "athlete": "Colleen Sostorics",
    "age": 30,
    "country": "Canada",
    "year": 2010,
    "date": "28/02/2010",
    "sport": "Ice Hockey",
    "gold": 1,
    "silver": 0,
    "bronze": 0,
    "total": 1
  },
  {
    "athlete": "Kim St-Pierre",
    "age": 31,
    "country": "Canada",
    "year": 2010,
    "date": "28/02/2010",
    "sport": "Ice Hockey",
    "gold": 1,
    "silver": 0,
    "bronze": 0,
    "total": 1
  },
  {
    "athlete": "Eric Staal",
    "age": 25,
    "country": "Canada",
    "year": 2010,
    "date": "28/02/2010",
    "sport": "Ice Hockey",
    "gold": 1,
    "silver": 0,
    "bronze": 0,
    "total": 1
  },
  {
    "athlete": "Shannon Szabados",
    "age": 23,
    "country": "Canada",
    "year": 2010,
    "date": "28/02/2010",
    "sport": "Ice Hockey",
    "gold": 1,
    "silver": 0,
    "bronze": 0,
    "total": 1
  },
  {
    "athlete": "Joe Thornton",
    "age": 30,
    "country": "Canada",
    "year": 2010,
    "date": "28/02/2010",
    "sport": "Ice Hockey",
    "gold": 1,
    "silver": 0,
    "bronze": 0,
    "total": 1
  },
  {
    "athlete": "Jonathan Toews",
    "age": 21,
    "country": "Canada",
    "year": 2010,
    "date": "28/02/2010",
    "sport": "Ice Hockey",
    "gold": 1,
    "silver": 0,
    "bronze": 0,
    "total": 1
  },
  {
    "athlete": "Sarah Vaillancourt",
    "age": 24,
    "country": "Canada",
    "year": 2010,
    "date": "28/02/2010",
    "sport": "Ice Hockey",
    "gold": 1,
    "silver": 0,
    "bronze": 0,
    "total": 1
  },
  {
    "athlete": "Catherine Ward",
    "age": 22,
    "country": "Canada",
    "year": 2010,
    "date": "28/02/2010",
    "sport": "Ice Hockey",
    "gold": 1,
    "silver": 0,
    "bronze": 0,
    "total": 1
  },
  {
    "athlete": "Shea Weber",
    "age": 24,
    "country": "Canada",
    "year": 2010,
    "date": "28/02/2010",
    "sport": "Ice Hockey",
    "gold": 1,
    "silver": 0,
    "bronze": 0,
    "total": 1
  },
  {
    "athlete": "Hayley Wickenheiser",
    "age": 31,
    "country": "Canada",
    "year": 2010,
    "date": "28/02/2010",
    "sport": "Ice Hockey",
    "gold": 1,
    "silver": 0,
    "bronze": 0,
    "total": 1
  },
  {
    "athlete": "Meghan Agosta",
    "age": 18,
    "country": "Canada",
    "year": 2006,
    "date": "26/02/2006",
    "sport": "Ice Hockey",
    "gold": 1,
    "silver": 0,
    "bronze": 0,
    "total": 1
  },
  {
    "athlete": "Gillian Apps",
    "age": 22,
    "country": "Canada",
    "year": 2006,
    "date": "26/02/2006",
    "sport": "Ice Hockey",
    "gold": 1,
    "silver": 0,
    "bronze": 0,
    "total": 1
  },
  {
    "athlete": "Jennifer Botterill",
    "age": 26,
    "country": "Canada",
    "year": 2006,
    "date": "26/02/2006",
    "sport": "Ice Hockey",
    "gold": 1,
    "silver": 0,
    "bronze": 0,
    "total": 1
  },
  {
    "athlete": "Cassie Campbell",
    "age": 32,
    "country": "Canada",
    "year": 2006,
    "date": "26/02/2006",
    "sport": "Ice Hockey",
    "gold": 1,
    "silver": 0,
    "bronze": 0,
    "total": 1
  },
  {
    "athlete": "Gillian Ferrari",
    "age": 25,
    "country": "Canada",
    "year": 2006,
    "date": "26/02/2006",
    "sport": "Ice Hockey",
    "gold": 1,
    "silver": 0,
    "bronze": 0,
    "total": 1
  },
  {
    "athlete": "Danielle Goyette",
    "age": 40,
    "country": "Canada",
    "year": 2006,
    "date": "26/02/2006",
    "sport": "Ice Hockey",
    "gold": 1,
    "silver": 0,
    "bronze": 0,
    "total": 1
  },
  {
    "athlete": "Jayna Hefford",
    "age": 28,
    "country": "Canada",
    "year": 2006,
    "date": "26/02/2006",
    "sport": "Ice Hockey",
    "gold": 1,
    "silver": 0,
    "bronze": 0,
    "total": 1
  },
  {
    "athlete": "Becky Kellar",
    "age": 31,
    "country": "Canada",
    "year": 2006,
    "date": "26/02/2006",
    "sport": "Ice Hockey",
    "gold": 1,
    "silver": 0,
    "bronze": 0,
    "total": 1
  },
  {
    "athlete": "Gina Kingsbury",
    "age": 24,
    "country": "Canada",
    "year": 2006,
    "date": "26/02/2006",
    "sport": "Ice Hockey",
    "gold": 1,
    "silver": 0,
    "bronze": 0,
    "total": 1
  },
  {
    "athlete": "Charlie Labonté",
    "age": 23,
    "country": "Canada",
    "year": 2006,
    "date": "26/02/2006",
    "sport": "Ice Hockey",
    "gold": 1,
    "silver": 0,
    "bronze": 0,
    "total": 1
  },
  {
    "athlete": "Carla MacLeod",
    "age": 23,
    "country": "Canada",
    "year": 2006,
    "date": "26/02/2006",
    "sport": "Ice Hockey",
    "gold": 1,
    "silver": 0,
    "bronze": 0,
    "total": 1
  },
  {
    "athlete": "Caroline Ouellette",
    "age": 26,
    "country": "Canada",
    "year": 2006,
    "date": "26/02/2006",
    "sport": "Ice Hockey",
    "gold": 1,
    "silver": 0,
    "bronze": 0,
    "total": 1
  },
  {
    "athlete": "Cherie Piper",
    "age": 24,
    "country": "Canada",
    "year": 2006,
    "date": "26/02/2006",
    "sport": "Ice Hockey",
    "gold": 1,
    "silver": 0,
    "bronze": 0,
    "total": 1
  },
  {
    "athlete": "Cheryl Pounder",
    "age": 29,
    "country": "Canada",
    "year": 2006,
    "date": "26/02/2006",
    "sport": "Ice Hockey",
    "gold": 1,
    "silver": 0,
    "bronze": 0,
    "total": 1
  },
  {
    "athlete": "Colleen Sostorics",
    "age": 26,
    "country": "Canada",
    "year": 2006,
    "date": "26/02/2006",
    "sport": "Ice Hockey",
    "gold": 1,
    "silver": 0,
    "bronze": 0,
    "total": 1
  },
  {
    "athlete": "Kim St-Pierre",
    "age": 27,
    "country": "Canada",
    "year": 2006,
    "date": "26/02/2006",
    "sport": "Ice Hockey",
    "gold": 1,
    "silver": 0,
    "bronze": 0,
    "total": 1
  },
  {
    "athlete": "Vicky Sunohara",
    "age": 35,
    "country": "Canada",
    "year": 2006,
    "date": "26/02/2006",
    "sport": "Ice Hockey",
    "gold": 1,
    "silver": 0,
    "bronze": 0,
    "total": 1
  },
  {
    "athlete": "Sarah Vaillancourt",
    "age": 20,
    "country": "Canada",
    "year": 2006,
    "date": "26/02/2006",
    "sport": "Ice Hockey",
    "gold": 1,
    "silver": 0,
    "bronze": 0,
    "total": 1
  },
  {
    "athlete": "Katie Weatherston",
    "age": 22,
    "country": "Canada",
    "year": 2006,
    "date": "26/02/2006",
    "sport": "Ice Hockey",
    "gold": 1,
    "silver": 0,
    "bronze": 0,
    "total": 1
  },
  {
    "athlete": "Hayley Wickenheiser",
    "age": 27,
    "country": "Canada",
    "year": 2006,
    "date": "26/02/2006",
    "sport": "Ice Hockey",
    "gold": 1,
    "silver": 0,
    "bronze": 0,
    "total": 1
  },
  {
    "athlete": "Dana Antal",
    "age": 24,
    "country": "Canada",
    "year": 2002,
    "date": "24/02/2002",
    "sport": "Ice Hockey",
    "gold": 1,
    "silver": 0,
    "bronze": 0,
    "total": 1
  },
  {
    "athlete": "Kelly Béchard",
    "age": 24,
    "country": "Canada",
    "year": 2002,
    "date": "24/02/2002",
    "sport": "Ice Hockey",
    "gold": 1,
    "silver": 0,
    "bronze": 0,
    "total": 1
  },
  {
    "athlete": "Rob Blake",
    "age": 32,
    "country": "Canada",
    "year": 2002,
    "date": "24/02/2002",
    "sport": "Ice Hockey",
    "gold": 1,
    "silver": 0,
    "bronze": 0,
    "total": 1
  },
  {
    "athlete": "Jennifer Botterill",
    "age": 22,
    "country": "Canada",
    "year": 2002,
    "date": "24/02/2002",
    "sport": "Ice Hockey",
    "gold": 1,
    "silver": 0,
    "bronze": 0,
    "total": 1
  },
  {
    "athlete": "Eric Brewer",
    "age": 22,
    "country": "Canada",
    "year": 2002,
    "date": "24/02/2002",
    "sport": "Ice Hockey",
    "gold": 1,
    "silver": 0,
    "bronze": 0,
    "total": 1
  },
  {
    "athlete": "Thérèse Brisson",
    "age": 35,
    "country": "Canada",
    "year": 2002,
    "date": "24/02/2002",
    "sport": "Ice Hockey",
    "gold": 1,
    "silver": 0,
    "bronze": 0,
    "total": 1
  },
  {
    "athlete": "Martin Brodeur",
    "age": 29,
    "country": "Canada",
    "year": 2002,
    "date": "24/02/2002",
    "sport": "Ice Hockey",
    "gold": 1,
    "silver": 0,
    "bronze": 0,
    "total": 1
  },
  {
    "athlete": "Cassie Campbell",
    "age": 28,
    "country": "Canada",
    "year": 2002,
    "date": "24/02/2002",
    "sport": "Ice Hockey",
    "gold": 1,
    "silver": 0,
    "bronze": 0,
    "total": 1
  },
  {
    "athlete": "Isabelle Chartrand",
    "age": 23,
    "country": "Canada",
    "year": 2002,
    "date": "24/02/2002",
    "sport": "Ice Hockey",
    "gold": 1,
    "silver": 0,
    "bronze": 0,
    "total": 1
  },
  {
    "athlete": "Lori Dupuis",
    "age": 29,
    "country": "Canada",
    "year": 2002,
    "date": "24/02/2002",
    "sport": "Ice Hockey",
    "gold": 1,
    "silver": 0,
    "bronze": 0,
    "total": 1
  },
  {
    "athlete": "Theo Fleury",
    "age": 33,
    "country": "Canada",
    "year": 2002,
    "date": "24/02/2002",
    "sport": "Ice Hockey",
    "gold": 1,
    "silver": 0,
    "bronze": 0,
    "total": 1
  },
  {
    "athlete": "Adam Foote",
    "age": 30,
    "country": "Canada",
    "year": 2002,
    "date": "24/02/2002",
    "sport": "Ice Hockey",
    "gold": 1,
    "silver": 0,
    "bronze": 0,
    "total": 1
  },
  {
    "athlete": "Simon Gagné",
    "age": 21,
    "country": "Canada",
    "year": 2002,
    "date": "24/02/2002",
    "sport": "Ice Hockey",
    "gold": 1,
    "silver": 0,
    "bronze": 0,
    "total": 1
  },
  {
    "athlete": "Danielle Goyette",
    "age": 36,
    "country": "Canada",
    "year": 2002,
    "date": "24/02/2002",
    "sport": "Ice Hockey",
    "gold": 1,
    "silver": 0,
    "bronze": 0,
    "total": 1
  },
  {
    "athlete": "Geraldine Heaney",
    "age": 34,
    "country": "Canada",
    "year": 2002,
    "date": "24/02/2002",
    "sport": "Ice Hockey",
    "gold": 1,
    "silver": 0,
    "bronze": 0,
    "total": 1
  },
  {
    "athlete": "Jayna Hefford",
    "age": 24,
    "country": "Canada",
    "year": 2002,
    "date": "24/02/2002",
    "sport": "Ice Hockey",
    "gold": 1,
    "silver": 0,
    "bronze": 0,
    "total": 1
  },
  {
    "athlete": "Jarome Iginla",
    "age": 24,
    "country": "Canada",
    "year": 2002,
    "date": "24/02/2002",
    "sport": "Ice Hockey",
    "gold": 1,
    "silver": 0,
    "bronze": 0,
    "total": 1
  },
  {
    "athlete": "Curtis Joseph",
    "age": 34,
    "country": "Canada",
    "year": 2002,
    "date": "24/02/2002",
    "sport": "Ice Hockey",
    "gold": 1,
    "silver": 0,
    "bronze": 0,
    "total": 1
  },
  {
    "athlete": "Ed Jovanovski",
    "age": 25,
    "country": "Canada",
    "year": 2002,
    "date": "24/02/2002",
    "sport": "Ice Hockey",
    "gold": 1,
    "silver": 0,
    "bronze": 0,
    "total": 1
  },
  {
    "athlete": "Paul Kariya",
    "age": 27,
    "country": "Canada",
    "year": 2002,
    "date": "24/02/2002",
    "sport": "Ice Hockey",
    "gold": 1,
    "silver": 0,
    "bronze": 0,
    "total": 1
  },
  {
    "athlete": "Becky Kellar",
    "age": 27,
    "country": "Canada",
    "year": 2002,
    "date": "24/02/2002",
    "sport": "Ice Hockey",
    "gold": 1,
    "silver": 0,
    "bronze": 0,
    "total": 1
  },
  {
    "athlete": "Mario Lemieux",
    "age": 36,
    "country": "Canada",
    "year": 2002,
    "date": "24/02/2002",
    "sport": "Ice Hockey",
    "gold": 1,
    "silver": 0,
    "bronze": 0,
    "total": 1
  },
  {
    "athlete": "Eric Lindros",
    "age": 28,
    "country": "Canada",
    "year": 2002,
    "date": "24/02/2002",
    "sport": "Ice Hockey",
    "gold": 1,
    "silver": 0,
    "bronze": 0,
    "total": 1
  },
  {
    "athlete": "Al MacInnis",
    "age": 38,
    "country": "Canada",
    "year": 2002,
    "date": "24/02/2002",
    "sport": "Ice Hockey",
    "gold": 1,
    "silver": 0,
    "bronze": 0,
    "total": 1
  },
  {
    "athlete": "Scott Niedermayer",
    "age": 28,
    "country": "Canada",
    "year": 2002,
    "date": "24/02/2002",
    "sport": "Ice Hockey",
    "gold": 1,
    "silver": 0,
    "bronze": 0,
    "total": 1
  },
  {
    "athlete": "Joe Nieuwendyk",
    "age": 35,
    "country": "Canada",
    "year": 2002,
    "date": "24/02/2002",
    "sport": "Ice Hockey",
    "gold": 1,
    "silver": 0,
    "bronze": 0,
    "total": 1
  },
  {
    "athlete": "Owen Nolan",
    "age": 29,
    "country": "Canada",
    "year": 2002,
    "date": "24/02/2002",
    "sport": "Ice Hockey",
    "gold": 1,
    "silver": 0,
    "bronze": 0,
    "total": 1
  },
  {
    "athlete": "Caroline Ouellette",
    "age": 22,
    "country": "Canada",
    "year": 2002,
    "date": "24/02/2002",
    "sport": "Ice Hockey",
    "gold": 1,
    "silver": 0,
    "bronze": 0,
    "total": 1
  },
  {
    "athlete": "Mike Peca",
    "age": 27,
    "country": "Canada",
    "year": 2002,
    "date": "24/02/2002",
    "sport": "Ice Hockey",
    "gold": 1,
    "silver": 0,
    "bronze": 0,
    "total": 1
  },
  {
    "athlete": "Cherie Piper",
    "age": 20,
    "country": "Canada",
    "year": 2002,
    "date": "24/02/2002",
    "sport": "Ice Hockey",
    "gold": 1,
    "silver": 0,
    "bronze": 0,
    "total": 1
  },
  {
    "athlete": "Cheryl Pounder",
    "age": 25,
    "country": "Canada",
    "year": 2002,
    "date": "24/02/2002",
    "sport": "Ice Hockey",
    "gold": 1,
    "silver": 0,
    "bronze": 0,
    "total": 1
  },
  {
    "athlete": "Chris Pronger",
    "age": 27,
    "country": "Canada",
    "year": 2002,
    "date": "24/02/2002",
    "sport": "Ice Hockey",
    "gold": 1,
    "silver": 0,
    "bronze": 0,
    "total": 1
  },
  {
    "athlete": "Joe Sakic",
    "age": 32,
    "country": "Canada",
    "year": 2002,
    "date": "24/02/2002",
    "sport": "Ice Hockey",
    "gold": 1,
    "silver": 0,
    "bronze": 0,
    "total": 1
  },
  {
    "athlete": "Brendan Shanahan",
    "age": 33,
    "country": "Canada",
    "year": 2002,
    "date": "24/02/2002",
    "sport": "Ice Hockey",
    "gold": 1,
    "silver": 0,
    "bronze": 0,
    "total": 1
  },
  {
    "athlete": "Tammy Lee Shewchuk",
    "age": 24,
    "country": "Canada",
    "year": 2002,
    "date": "24/02/2002",
    "sport": "Ice Hockey",
    "gold": 1,
    "silver": 0,
    "bronze": 0,
    "total": 1
  },
  {
    "athlete": "Sami Jo Small",
    "age": 25,
    "country": "Canada",
    "year": 2002,
    "date": "24/02/2002",
    "sport": "Ice Hockey",
    "gold": 1,
    "silver": 0,
    "bronze": 0,
    "total": 1
  },
  {
    "athlete": "Ryan Smyth",
    "age": 25,
    "country": "Canada",
    "year": 2002,
    "date": "24/02/2002",
    "sport": "Ice Hockey",
    "gold": 1,
    "silver": 0,
    "bronze": 0,
    "total": 1
  },
  {
    "athlete": "Colleen Sostorics",
    "age": 22,
    "country": "Canada",
    "year": 2002,
    "date": "24/02/2002",
    "sport": "Ice Hockey",
    "gold": 1,
    "silver": 0,
    "bronze": 0,
    "total": 1
  },
  {
    "athlete": "Kim St-Pierre",
    "age": 23,
    "country": "Canada",
    "year": 2002,
    "date": "24/02/2002",
    "sport": "Ice Hockey",
    "gold": 1,
    "silver": 0,
    "bronze": 0,
    "total": 1
  },
  {
    "athlete": "Vicky Sunohara",
    "age": 31,
    "country": "Canada",
    "year": 2002,
    "date": "24/02/2002",
    "sport": "Ice Hockey",
    "gold": 1,
    "silver": 0,
    "bronze": 0,
    "total": 1
  },
  {
    "athlete": "Hayley Wickenheiser",
    "age": 23,
    "country": "Canada",
    "year": 2002,
    "date": "24/02/2002",
    "sport": "Ice Hockey",
    "gold": 1,
    "silver": 0,
    "bronze": 0,
    "total": 1
  },
  {
    "athlete": "Steve Yzerman",
    "age": 36,
    "country": "Canada",
    "year": 2002,
    "date": "24/02/2002",
    "sport": "Ice Hockey",
    "gold": 1,
    "silver": 0,
    "bronze": 0,
    "total": 1
  }
]
