{
    "eventHandlers": [
        {
            "name": "firstDataRendered",
            "handlerName": "onFirstDataRendered",
            "handler": "function onFirstDataRendered(params) {\n    setTimeout(function () {\n        params.api.getDisplayedRowAtIndex(0).setExpanded(true);\n    }, 0);\n    setInterval(function () {\n        if (!allRowData) {\n            return;\n        }\n        const data = allRowData[0];\n        const newCallRecords = [];\n        data.callRecords.forEach(function (record, index) {\n            newCallRecords.push({\n                name: record.name,\n                callId: record.callId,\n                duration: record.duration + index % 2,\n                switchCode: record.switchCode,\n                direction: record.direction,\n                number: record.number\n            });\n        });\n        data.callRecords = newCallRecords;\n        data.calls++;\n        const tran = { update: [data] };\n        params.api.applyTransaction(tran);\n    }, 2000);\n}"
        }
    ],
    "properties": [
        {
            "name": "columnDefs",
            "value": "[\n        {\n            field: \"name\",\n            cellRenderer: \"agGroupCellRenderer\"\n        },\n        { field: \"account\" },\n        { field: \"calls\" },\n        {\n            field: \"minutes\",\n            valueFormatter: \"x.toLocaleString() + 'm'\"\n        }\n    ]"
        },
        { "name": "defaultColDef", "value": "{ flex: 1 }" },
        { "name": "getRowNodeId", "value": "function (data) {\n        return data.account;\n    }" },
        { "name": "masterDetail", "value": "true" },
        { "name": "enableCellChangeFlash", "value": "true" },
        {
            "name": "detailCellRendererParams",
            "value": "{\n        refreshStrategy: \"rows\",\n        template: function (params) {\n            return \"<div class=\\\"ag-details-row ag-details-row-fixed-height\\\">\" + \"<div style=\\\"padding: 4px; font-weight: bold;\\\">\" + params.data.name + \" \" + params.data.calls + \" calls</div>\" + \"<div ref=\\\"eDetailGrid\\\" class=\\\"ag-details-grid ag-details-grid-fixed-height\\\"/>\" + \"</div>\";\n        },\n        detailGridOptions: {\n            rowSelection: \"multiple\",\n            enableCellChangeFlash: true,\n            immutableData: true,\n            getRowNodeId: function (data) {\n                return data.callId;\n            },\n            columnDefs: [\n                {\n                    field: \"callId\",\n                    checkboxSelection: true\n                },\n                { field: \"direction\" },\n                {\n                    field: \"number\",\n                    minWidth: 150\n                },\n                {\n                    field: \"duration\",\n                    valueFormatter: \"x.toLocaleString() + 's'\"\n                },\n                {\n                    field: \"switchCode\",\n                    minWidth: 150\n                }\n            ],\n            defaultColDef: {\n                flex: 1,\n                sortable: true\n            }\n        },\n        getDetailRowData: function (params) {\n            params.successCallback(params.data.callRecords);\n        }\n    }"
        }
    ],
    "components": [],
    "defaultColDef": "{ flex: 1 }",
    "globalComponents": [],
    "parsedColDefs": "[\n        {\n            field: \"name\",\n            cellRenderer: \"agGroupCellRenderer\"\n        },\n        { field: \"account\" },\n        { field: \"calls\" },\n        {\n            field: \"minutes\",\n            valueFormatter: \"x.toLocaleString() + 'm'\"\n        }\n    ]",
    "instanceMethods": [],
    "externalEventHandlers": [],
    "utils": ["let allRowData;"],
    "data": {
        "url": "'https://www.ag-grid.com/example-assets/master-detail-data.json'",
        "callback": "{\n    allRowData = data;\n    params.api.setRowData(data);\n}"
    },
    "template": "GRID_TEMPLATE_PLACEHOLDER\n",
    "gridSettings": {
        "width": "100%",
        "height": "100%",
        "theme": "ag-theme-alpine",
        "enterprise": true,
        "exampleHeight": 550,
        "modules": ["clientside", "masterdetail", "menu", "columnpanel"]
    }
}
